QianghuaXuexiDaolunZhongwenDierBan/README.md
QianghuaXuexiDaolunZhongwenDierBan/__init__.py
QianghuaXuexiDaolunZhongwenDierBan/__main__.py
QianghuaXuexiDaolunZhongwenDierBan/file.epub
QianghuaXuexiDaolunZhongwenDierBan/index.html
QianghuaXuexiDaolunZhongwenDierBan/css/__init__.py
QianghuaXuexiDaolunZhongwenDierBan/css/annotations.css
QianghuaXuexiDaolunZhongwenDierBan/css/main.css
QianghuaXuexiDaolunZhongwenDierBan/css/normalize.css
QianghuaXuexiDaolunZhongwenDierBan/css/popup.css
QianghuaXuexiDaolunZhongwenDierBan/font/__init__.py
QianghuaXuexiDaolunZhongwenDierBan/font/fontello.eot
QianghuaXuexiDaolunZhongwenDierBan/font/fontello.svg
QianghuaXuexiDaolunZhongwenDierBan/font/fontello.ttf
QianghuaXuexiDaolunZhongwenDierBan/font/fontello.woff
QianghuaXuexiDaolunZhongwenDierBan/img/__init__.py
QianghuaXuexiDaolunZhongwenDierBan/img/annotator-glyph-sprite.png
QianghuaXuexiDaolunZhongwenDierBan/img/annotator-icon-sprite.png
QianghuaXuexiDaolunZhongwenDierBan/img/apple-touch-icon.png
QianghuaXuexiDaolunZhongwenDierBan/img/cancelfullscreen.png
QianghuaXuexiDaolunZhongwenDierBan/img/close.png
QianghuaXuexiDaolunZhongwenDierBan/img/fullscreen.png
QianghuaXuexiDaolunZhongwenDierBan/img/loader.gif
QianghuaXuexiDaolunZhongwenDierBan/img/menu-icon.png
QianghuaXuexiDaolunZhongwenDierBan/img/save.png
QianghuaXuexiDaolunZhongwenDierBan/img/saved.png
QianghuaXuexiDaolunZhongwenDierBan/img/settings-s.png
QianghuaXuexiDaolunZhongwenDierBan/img/settings.png
QianghuaXuexiDaolunZhongwenDierBan/img/star.png
QianghuaXuexiDaolunZhongwenDierBan/js/__init__.py
QianghuaXuexiDaolunZhongwenDierBan/js/epub.js
QianghuaXuexiDaolunZhongwenDierBan/js/epub.min.js
QianghuaXuexiDaolunZhongwenDierBan/js/epub.min.map
QianghuaXuexiDaolunZhongwenDierBan/js/hooks.min.js
QianghuaXuexiDaolunZhongwenDierBan/js/hooks.min.map
QianghuaXuexiDaolunZhongwenDierBan/js/reader.js
QianghuaXuexiDaolunZhongwenDierBan/js/reader.js.map
QianghuaXuexiDaolunZhongwenDierBan/js/reader.min.js
qianghua_xuexi_daolun_zhongwen_dier_ban-2024.3.5.0.dist-info/METADATA
qianghua_xuexi_daolun_zhongwen_dier_ban-2024.3.5.0.dist-info/WHEEL
qianghua_xuexi_daolun_zhongwen_dier_ban-2024.3.5.0.dist-info/entry_points.txt
qianghua_xuexi_daolun_zhongwen_dier_ban-2024.3.5.0.dist-info/top_level.txt
qianghua_xuexi_daolun_zhongwen_dier_ban-2024.3.5.0.dist-info/RECORD
